{"name":"SealDrop - KOTH","tagline":"SealDrop KOTH | Version: 1.0 | Arma 3 Version: 1.52 | extDB Version: 66","body":"<h1 align=\"center\">SealDrop KOTH</h1>\r\n<p align=\"center\">\r\n    <a href=\"https://github.com/DeadP4xel/SealDrop-KOTH/wiki/Changelog\">\r\n    <img src=\"http://storage.sealdrop.de/koth/koth_icon_version.png\" alt=\"Changelog\" />\r\n  </a>\r\n    <a href=\"https://creativecommons.org/licenses/by-nc-nd/4.0/deed.en_US\">\r\n    <img src=\"http://storage.sealdrop.de/koth/koth_icon_license.png\" alt=\"License\" />\r\n  </a>\r\n</p>\r\nSealDrop KOTH is the first OpenSource release of the successful KingOfTheHill Mission. SealDrop KOTH is a gamemode for Arma 3 where a team of players can fight against each other to earn XP and levels. \r\n\r\nSealDrop KOTH was written by [DeadP4xel](https://github.com/DeadP4xel).\r\n\r\n###Documentation / Wiki</br>\r\nHere you can find all usefull informations about KOTH. [Visit the wiki](https://github.com/DeadP4xel/SealDrop-KOTH/wiki)\r\n\r\n###License\r\nSealDrop KOTH by DeadP4xel is licensed under a Creative Commons Attribution-NonCommercial-NoDerivatives 4.0 International License</br>\r\nhttps://creativecommons.org/licenses/by-nc-nd/4.0/deed.en_US</br>\r\n\r\n###Installation\r\nYou can find the installation steps here: [Installation Guide](https://github.com/DeadP4xel/SealDrop-KOTH/wiki#installation)\r\n\r\n###Special Thanks\r\n* [Tonic](https://github.com/TAWTonic) for the CfgFetch script.\r\n* [Torndeco](https://github.com/Torndeco) for extDB2.\r\n* [Aeroson](https://github.com/aeroson) for the vehicle unflip script.\r\n* [KiloSwiss](https://github.com/KiloSwiss) for the NoVoiceInChat script.\r\n* [infiSTAR](https://github.com/infiSTAR) for the help with the GlobalKillCounter.\r\n* [Sp4rkY](https://github.com/SPKcoding) for the help with misc stuff for KOTH.\r\n","google":"","note":"Don't delete this file! It's used internally to help with page regeneration."}